sqwrl/__init__.py
sqwrl-0.1.0.dist-info/LICENSE.txt
sqwrl-0.1.0.dist-info/METADATA
sqwrl-0.1.0.dist-info/WHEEL
sqwrl-0.1.0.dist-info/top_level.txt
sqwrl-0.1.0.dist-info/RECORD
