Metadata-Version: 2.1
Name: sqwrl
Version: 0.1.0
Summary: Sqlachemy Query WRapper Library - pandas-like SQL
Home-page: https://github.com/quantology/sqwrl
Author: Michael Tartre
Author-email: michael@enkratic.com
License: bsd-3-clause
Platform: UNKNOWN
Classifier: Programming Language :: Python :: 3 :: Only
Classifier: Programming Language :: Python :: 3.3
Classifier: Programming Language :: Python :: 3.4
Classifier: Programming Language :: Python :: 3.5
Classifier: Programming Language :: Python :: 3.6
Classifier: Programming Language :: SQL
Classifier: Intended Audience :: Developers
Classifier: License :: OSI Approved :: BSD License
Classifier: Topic :: Software Development :: Libraries
Classifier: Topic :: Utilities
Classifier: Development Status :: 3 - Alpha
Classifier: Operating System :: OS Independent
Classifier: Topic :: Software Development
Classifier: Topic :: Software Development :: Code Generators
Classifier: Topic :: Database
Classifier: Topic :: Database :: Front-Ends
Requires-Dist: pandas
Requires-Dist: numpy
Requires-Dist: sqlalchemy
Requires-Dist: sympy
Requires-Dist: toolz
Requires-Dist: datashape
